[
	{
		"uID": "q-1",
		"title": "Annoying Bandits",
		"description": "Defeat two bandits located south of the camp",
		"experience": 100,
		"gold": 5,
		"amount": 2,
		"target": ["6f3e3058-62ce-43da-bd38-d5c822c95175"],
		"talkTo": null,
		"explore": null,
		"questGiver": "other-quest-giver",
		"type": 0
	},
	{
		"uID": "q-2",
		"title": "Stealing our money",
		"description": "Defeat bandit leader located north of the camp",
		"experience": 200,
		"gold": 15,
		"amount": 1,
		"target": ["6f3e3058-62ce-43da-bd38-d5c822c95175"],
		"talkTo": null,
		"explore": null,
		"questGiver": "eb6a3d3c-f336-4a7a-af93-8c5aba6371d2",
		"type": 0
	}

]